{"cameraMode":{"drawMode":0,"name":"Shaded","section":"Shading Mode"},"sceneLighting":false,"audioPlay":false,"sceneViewState":{"m_AlwaysRefresh":false,"showFog":true,"showSkybox":false,"showFlares":true,"showImageEffects":true,"showParticleSystems":true,"showVisualEffectGraphs":true,"m_FxEnabled":true},"in2DMode":false,"pivot":{"x":-0.00019085407257080078,"y":1.0314147472381592,"z":-0.012931138277053833},"rotation":{"x":-0.1392880529165268,"y":-0.03059643693268299,"z":0.004305787850171328,"w":-0.9897692799568176},"size":1.562317132949829,"orthographic":false}