[{"id":0,"isuse":1,"issell":1,"isequip":0,"num":9,"showType":"bag","icon":"1001","name":"红药"},{"id":1,"isuse":1,"issell":1,"isequip":0,"num":9,"showType":"bag","icon":"1002","name":"蓝药"},{"id":2,"isuse":0,"issell":1,"isequip":0,"num":10,"showType":"bag","icon":"5001","name":"绿宝石"},{"id":3,"isuse":0,"issell":1,"isequip":0,"num":10,"showType":"bag","icon":"5002","name":"蓝宝石"},{"id":4,"isuse":0,"issell":1,"isequip":0,"num":10,"showType":"shop","icon":"5003","name":"黄宝石"},{"id":5,"isuse":1,"issell":1,"isequip":1,"num":10,"showType":"shop","icon":"10100","name":"武器"}]